aiomql/__init__.py
aiomql/_utils.py
aiomql/contrib/__init__.py
aiomql/contrib/candle_patterns/__init__.py
aiomql/contrib/candle_patterns/fractals.py
aiomql/contrib/strategies/__init__.py
aiomql/contrib/strategies/chaos.py
aiomql/contrib/strategies/finger_trap.py
aiomql/contrib/symbols/__init__.py
aiomql/contrib/symbols/forex_symbol.py
aiomql/contrib/traders/__init__.py
aiomql/contrib/traders/scalp_trader.py
aiomql/contrib/traders/simple_trader.py
aiomql/contrib/utils/__init__.py
aiomql/contrib/utils/tracker.py
aiomql/core/__init__.py
aiomql/core/_core.py
aiomql/core/base.py
aiomql/core/config.py
aiomql/core/constants.py
aiomql/core/errors.py
aiomql/core/exceptions.py
aiomql/core/meta_backtester.py
aiomql/core/meta_trader.py
aiomql/core/models.py
aiomql/core/task_queue.py
aiomql/core/backtesting/__init__.py
aiomql/core/backtesting/backtest_account.py
aiomql/core/backtesting/backtest_controller.py
aiomql/core/backtesting/backtest_engine.py
aiomql/core/backtesting/get_data.py
aiomql/core/backtesting/trades_manager.py
aiomql/lib/__init__.py
aiomql/lib/account.py
aiomql/lib/backtester.py
aiomql/lib/bot.py
aiomql/lib/candle.py
aiomql/lib/executor.py
aiomql/lib/history.py
aiomql/lib/order.py
aiomql/lib/positions.py
aiomql/lib/ram.py
aiomql/lib/result.py
aiomql/lib/sessions.py
aiomql/lib/strategy.py
aiomql/lib/symbol.py
aiomql/lib/terminal.py
aiomql/lib/ticks.py
aiomql/lib/trade_records.py
aiomql/lib/trader.py
aiomql-4.1.0.dist-info/LICENSE
aiomql-4.1.0.dist-info/METADATA
aiomql-4.1.0.dist-info/WHEEL
aiomql-4.1.0.dist-info/top_level.txt
aiomql-4.1.0.dist-info/RECORD
