Metadata-Version: 2.1
Name: aiomql
Version: 4.1.0
Summary: Asynchronous MetaTrader5 library and Algorithmic Trading Framework
Author-email: Ichinga Samuel <ichingasamuel@gmail.com>
Project-URL: Homepage, https://github.com/Ichinga-Samuel/aiomql
Project-URL: Bug Tracker, https://github.com/Ichinga-Samuel/aiomql/issues
Keywords: MetaTrader5,Asynchronous,Algorithmic Trading,Trading Bot,Backtesting,Technical Analysis,Forex,Stocks,Cryptocurrency,Futures,Options
Classifier: Programming Language :: Python :: 3
Classifier: License :: OSI Approved :: MIT License
Classifier: Operating System :: OS Independent
Requires-Python: >=3.11
License-File: LICENSE
Requires-Dist: MetaTrader5 >=5.0.37
Requires-Dist: pandas >=1.5.0
Requires-Dist: pandas-ta >=0.3.14b0
